topsis_isha/__init__.py
topsis_isha/topsis.py
topsis_isha_102303007-1.0.0.dist-info/METADATA
topsis_isha_102303007-1.0.0.dist-info/WHEEL
topsis_isha_102303007-1.0.0.dist-info/entry_points.txt
topsis_isha_102303007-1.0.0.dist-info/top_level.txt
topsis_isha_102303007-1.0.0.dist-info/RECORD
