Metadata-Version: 2.4
Name: topsis-isha-102303007
Version: 1.0.0
Summary: A Python package implementing TOPSIS (Technique for Order Preference by Similarity to Ideal Solution)
Author: Isha Gupta
Author-email: igupta1_be23@thapar.edu
Classifier: Programming Language :: Python :: 3
Classifier: License :: OSI Approved :: MIT License
Classifier: Operating System :: OS Independent
Requires-Python: >=3.8
Requires-Dist: pandas
Requires-Dist: numpy
Dynamic: author
Dynamic: author-email
Dynamic: classifier
Dynamic: description-content-type
Dynamic: requires-dist
Dynamic: requires-python
Dynamic: summary
